setup.py
dsnd_statsprob/Binomialdistribution.py
dsnd_statsprob/Gaussiandistribution.py
dsnd_statsprob/Generaldistribution.py
dsnd_statsprob/__init__.py
dsnd_statsprob.egg-info/PKG-INFO
dsnd_statsprob.egg-info/SOURCES.txt
dsnd_statsprob.egg-info/dependency_links.txt
dsnd_statsprob.egg-info/not-zip-safe
dsnd_statsprob.egg-info/top_level.txt