Metadata-Version: 1.0
Name: dsnd-statsprob
Version: 0.1
Summary: Gaussian and Binomial distributions
Home-page: UNKNOWN
Author: Navneet Sajwan
Author-email: UNKNOWN
License: UNKNOWN
Platform: UNKNOWN
